ckrett/__init__.py
ckrett-1.5.0.dist-info/LICENSE
ckrett-1.5.0.dist-info/METADATA
ckrett-1.5.0.dist-info/WHEEL
ckrett-1.5.0.dist-info/top_level.txt
ckrett-1.5.0.dist-info/RECORD
