Metadata-Version: 2.1
Name: ckrett
Version: 1.5.0
Summary: a basic ciphering/deciphering tool
Home-page: https://github.com/sasivatsal7122/ckret-library-pypi
Author: Sasi Vatsal
Author-email: sasivatsal7122@gmail.com
License: MIT
Keywords: ckrett
Platform: UNKNOWN
Classifier: Development Status :: 5 - Production/Stable
Classifier: Intended Audience :: Education
Classifier: Operating System :: Microsoft :: Windows :: Windows 10
Classifier: License :: OSI Approved :: MIT License
Classifier: Programming Language :: Python :: 3
License-File: LICENSE
Requires-Dist: pyttsx3
Requires-Dist: pipwin
